fluxterm/__init__.py
fluxterm/app.py
fluxterm/cli.py
fluxterm/command.py
fluxterm/defaults.py
fluxterm/utils.py
fluxterm/version.py
fluxterm/assets/__init__.py
fluxterm/assets/flux-commands.yaml
fluxterm/assets/fluxbird-small.png
fluxterm/assets/fluxterm.tcss
fluxterm/screen/__init__.py
fluxterm/screen/browser.py
fluxterm/screen/documentation.py
fluxterm/screen/fortune.py
fluxterm/screen/jobs.py
fluxterm-0.0.1.dist-info/LICENSE
fluxterm-0.0.1.dist-info/METADATA
fluxterm-0.0.1.dist-info/NOTICE
fluxterm-0.0.1.dist-info/WHEEL
fluxterm-0.0.1.dist-info/entry_points.txt
fluxterm-0.0.1.dist-info/top_level.txt
fluxterm-0.0.1.dist-info/RECORD
