Metadata-Version: 2.1
Name: fluxterm
Version: 0.0.1
Summary: Terminal application to interact with Flux jobs, cheat sheets, code, and good fortune
Home-page: https://github.com/converged-computing/flux-term
Author: Vanessa Sochat
Author-email: vsoch@users.noreply.github.com
Maintainer: Vanessa Sochat
License: LICENSE
Keywords: Flux framework,HPC,workload manager,jobs queue,textual
Classifier: Intended Audience :: Science/Research
Classifier: Intended Audience :: Developers
Classifier: License :: OSI Approved :: Mozilla Public License 2.0 (MPL 2.0)
Classifier: Programming Language :: Python
Classifier: Topic :: Software Development
Classifier: Topic :: Scientific/Engineering
Classifier: Operating System :: Unix
Classifier: Programming Language :: Python :: 3.6
License-File: LICENSE
License-File: NOTICE
Requires-Dist: textual-dev
Requires-Dist: pyaml
Requires-Dist: rich-pixels
Provides-Extra: all
Requires-Dist: textual-dev ; extra == 'all'
Requires-Dist: pyaml ; extra == 'all'
Requires-Dist: rich-pixels ; extra == 'all'
Requires-Dist: pytest >=4.6.2 ; extra == 'all'
